setup.py
greenhouseAccessFile.egg-info/PKG-INFO
greenhouseAccessFile.egg-info/SOURCES.txt
greenhouseAccessFile.egg-info/dependency_links.txt
greenhouseAccessFile.egg-info/not-zip-safe
greenhouseAccessFile.egg-info/top_level.txt
greenhouseEI/__init__.py
greenhouseEI/tools.py