Metadata-Version: 1.0
Name: greenhouseAccessFile
Version: 0.1
Summary: access any file in the zip file of Green House
Home-page: https://github.com/cseseniordesign/plant-phenotyping/tree/master/greenhouseEI
Author: YinchaoH
Author-email: yhe@huskers.unl.edu
License: APACHE2.0
Platform: UNKNOWN
